.gitignore
LICENSE
README.md
SLOPpy_Run.py
extra_requirements.txt
requirements.txt
setup.py
SLOPpy/__init__.py
SLOPpy/check_differential_refraction.py
SLOPpy/clv_rm_modelling.py
SLOPpy/clv_rm_models.py
SLOPpy/clv_rm_models_doubleprecision.py
SLOPpy/clv_rm_models_lines.py
SLOPpy/compare_clv_rm_effects.py
SLOPpy/config_default.py
SLOPpy/differential_refraction.bkp.py
SLOPpy/differential_refraction.py
SLOPpy/differential_refraction_preparation.py
SLOPpy/interstellar_lines.bkp.py
SLOPpy/interstellar_lines.py
SLOPpy/master_out.py
SLOPpy/pca_preparation.py
SLOPpy/prepare_datasets.py
SLOPpy/quick_transmission.py
SLOPpy/second_telluric_correction_on_transmission.py
SLOPpy/sky_correction.py
SLOPpy/sloppy_run.py
SLOPpy/spectra_lightcurve.py
SLOPpy/spectra_lightcurve_average.py
SLOPpy/spectra_lightcurve_bkp.py
SLOPpy/sysrem_correction.py
SLOPpy/telluric_airmass_observerRF.py
SLOPpy/telluric_airmass_observerRF_chunks.py
SLOPpy/telluric_airmass_stellarRF.py
SLOPpy/telluric_molecfit_coadd.py
SLOPpy/telluric_molecfit_preparation.py
SLOPpy/telluric_molecfit_v1_coadd.py
SLOPpy/telluric_molecfit_v1_preparation.py
SLOPpy/telluric_observerRF_skycalc.py
SLOPpy/telluric_template.py
SLOPpy/telluric_template_alternative.py
SLOPpy/transmission_binned_mcmc.py
SLOPpy/transmission_lightcurve.py
SLOPpy/transmission_lightcurve_average.py
SLOPpy/transmission_mcmc.py
SLOPpy/transmission_spectrum.py
SLOPpy/transmission_spectrum_average.py
SLOPpy/transmission_spectrum_preparation.py
SLOPpy/transmission_spectrum_shortcuts.py
SLOPpy/write_output_spectra.py
SLOPpy/write_output_transmission.py
SLOPpy/instruments/ESPRESSO.py
SLOPpy/instruments/HARPN_DRSv3.py
SLOPpy/instruments/HARPS_DRSv3.py
SLOPpy/instruments/PEPSI_reduced.py
SLOPpy/instruments/common_DRSv3.py
SLOPpy/instruments/get_data.py
SLOPpy/subroutines/__init__.py
SLOPpy/subroutines/bayesian_emcee.py
SLOPpy/subroutines/clv_rm_subroutines.py
SLOPpy/subroutines/common.py
SLOPpy/subroutines/constants.py
SLOPpy/subroutines/eso_skycalc_cli.py
SLOPpy_package.egg-info/PKG-INFO
SLOPpy_package.egg-info/SOURCES.txt
SLOPpy_package.egg-info/dependency_links.txt
SLOPpy_package.egg-info/entry_points.txt
SLOPpy_package.egg-info/not-zip-safe
SLOPpy_package.egg-info/requires.txt
SLOPpy_package.egg-info/top_level.txt
