Metadata-Version: 2.2
Name: SLOPpy-package
Version: 1.5.1
Summary: SLOPpy: Spectral Lines Of Planets with python
Home-page: https://github.com/LucaMalavolta/SLOPpy
Author: Daniela Sicilia, Luca Malavolta, et al.
Author-email: daniela.sicilia@inaf.it, luca.malavolta@unipd.it
License: MIT License
Classifier: Development Status :: 5 - Production/Stable
Classifier: Intended Audience :: Science/Research
Classifier: Topic :: Scientific/Engineering
Classifier: Operating System :: OS Independent
Classifier: Programming Language :: Python :: 3
License-File: LICENSE
Requires-Dist: numpy==1.26.4
Requires-Dist: numba>=0.55.1
Requires-Dist: scipy>=1.8.1
Requires-Dist: matplotlib>=3.5.2
Requires-Dist: astropy>=5.1
Requires-Dist: astroquery>=0.4
Requires-Dist: pyerfa>=2.0
Requires-Dist: argparse>=1.4
Requires-Dist: oyaml>=1.0
Requires-Dist: emcee>=3.1.2
Requires-Dist: pyyaml
Requires-Dist: h5py>=3.7.0
Requires-Dist: tqdm>=4.60
Requires-Dist: pygtc>=0.4.1
Requires-Dist: jaxlib==0.4.31
Requires-Dist: jax==0.4.31
Requires-Dist: tinygp>=0.3.0
Requires-Dist: PyAstronomy>=0.18
Requires-Dist: ordered-set
Requires-Dist: scikit-learn
Dynamic: author
Dynamic: author-email
Dynamic: classifier
Dynamic: description
Dynamic: description-content-type
Dynamic: home-page
Dynamic: license
Dynamic: requires-dist
Dynamic: summary
